analyzers/README.md
analyzers/__init__.py
analyzers/ast_utils.py
analyzers/base.py
analyzers/go_analyzer.py
analyzers/java_analyzer.py
analyzers/mcp_integration.py
analyzers/python_analyzer.py
analyzers/rust_analyzer.py
analyzers/typescript_analyzer.py
cli/__init__.py
cli/__version__.py
cli/enhanced_cli.py
cli/main.py
cli/commands/generate.py
core/__init__.py
core/auth.py
core/decorators.py
core/errors.py
core/health.py
core/logging_config.py
core/metrics.py
core/privacy.py
core/rate_limiter.py
core/retry.py
core/security.py
core/validation.py
core/cache/CACHE_ARCHITECTURE.md
core/cache/__init__.py
core/cache/decorators.py
core/cache/integration.py
core/cache/mcp_cache.py
core/cache/mcp_cache_integration.py
core/cache/redis_client.py
core/database/query_optimizer.py
core/mcp/__init__.py
core/mcp/async_server.py
core/mcp/handlers.py
core/mcp/server.py
core/middleware/__init__.py
core/middleware/error_middleware.py
core/performance/memory_manager.py
core/performance/metrics.py
core/standards/README_RULE_ENGINE.md
core/standards/README_SEMANTIC_SEARCH.md
core/standards/__init__.py
core/standards/analytics.py
core/standards/async_semantic_search.py
core/standards/cross_referencer.py
core/standards/engine.py
core/standards/models.py
core/standards/rule_engine.py
core/standards/search_integration.py
core/standards/semantic_search.py
core/standards/sync.py
core/standards/token_optimizer.py
core/standards/vector_index_cache.py
core/standards/versioning.py
generators/__init__.py
generators/base.py
generators/engine.py
generators/metadata.py
generators/quality_assurance.py
generators/validator.py
mcp_standards_server-1.0.1.dist-info/licenses/LICENSE
mcp_standards_server-1.0.1.dist-info/METADATA
mcp_standards_server-1.0.1.dist-info/WHEEL
mcp_standards_server-1.0.1.dist-info/entry_points.txt
mcp_standards_server-1.0.1.dist-info/top_level.txt
mcp_standards_server-1.0.1.dist-info/RECORD
