Metadata-Version: 2.4
Name: mcp-standards-server
Version: 1.0.1
Summary: A Model Context Protocol server for intelligent access to development standards
Author-email: William Zujkowski <williamzujkowski@users.noreply.github.com>
Maintainer-email: William Zujkowski <williamzujkowski@users.noreply.github.com>
License: MIT
Project-URL: Homepage, https://github.com/williamzujkowski/mcp-standards-server
Project-URL: Repository, https://github.com/williamzujkowski/mcp-standards-server
Project-URL: Issues, https://github.com/williamzujkowski/mcp-standards-server/issues
Keywords: mcp,model-context-protocol,development-standards,llm,ai-tools,code-quality,software-standards,compliance,best-practices,semantic-search,code-standards,nist,software-quality,testing,code-review
Classifier: Development Status :: 5 - Production/Stable
Classifier: Intended Audience :: Developers
Classifier: Topic :: Software Development :: Libraries
Classifier: Topic :: Software Development :: Libraries :: Python Modules
Classifier: Topic :: Software Development :: Quality Assurance
Classifier: Topic :: Text Processing :: Linguistic
Classifier: Topic :: Scientific/Engineering :: Artificial Intelligence
Classifier: License :: OSI Approved :: MIT License
Classifier: Programming Language :: Python :: 3
Classifier: Programming Language :: Python :: 3.10
Classifier: Programming Language :: Python :: 3.11
Classifier: Programming Language :: Python :: 3.12
Classifier: Operating System :: OS Independent
Classifier: Environment :: Console
Classifier: Framework :: AsyncIO
Classifier: Typing :: Typed
Requires-Python: >=3.10
License-File: LICENSE
Requires-Dist: mcp>=0.1.0
Requires-Dist: pydantic<2.12.0,>=2.6.0
Requires-Dist: redis>=6.2.0
Requires-Dist: PyYAML>=6.0
Requires-Dist: chromadb>=0.4.0
Requires-Dist: sentence-transformers>=2.2.0
Requires-Dist: transformers>=4.53.2
Requires-Dist: tiktoken>=0.4.0
Requires-Dist: tree-sitter>=0.20.0
Requires-Dist: aiofiles>=23.0.0
Requires-Dist: jsonschema>=4.0.0
Requires-Dist: aiohttp>=3.12.14
Requires-Dist: scikit-learn>=1.7.0
Requires-Dist: numpy>=2.0.0
Requires-Dist: nltk>=3.9.0
Requires-Dist: fuzzywuzzy>=0.18.0
Requires-Dist: python-Levenshtein>=0.25.0
Requires-Dist: PyJWT>=2.10.0
Requires-Dist: aiosqlite>=0.19.0
Requires-Dist: asyncpg>=0.29.0
Requires-Dist: aiomysql>=0.2.0
Requires-Dist: sqlalchemy>=2.0.0
Requires-Dist: PyGithub>=2.6.1
Requires-Dist: requests>=2.32.4
Requires-Dist: prometheus_client>=0.16.0
Requires-Dist: pympler>=1.0.0
Requires-Dist: memory-profiler>=0.60.0
Requires-Dist: faiss-cpu>=1.7.0
Requires-Dist: psutil>=5.9.0
Requires-Dist: msgpack>=1.0.0
Provides-Extra: dev
Requires-Dist: pytest>=7.0; extra == "dev"
Requires-Dist: pytest-asyncio>=0.21.0; extra == "dev"
Requires-Dist: pytest-benchmark>=4.0.0; extra == "dev"
Requires-Dist: pytest-timeout>=2.1.0; extra == "dev"
Requires-Dist: pytest-cov>=4.0.0; extra == "dev"
Requires-Dist: coverage[toml]>=7.0; extra == "dev"
Requires-Dist: black==24.10.0; extra == "dev"
Requires-Dist: ruff>=0.1.0; extra == "dev"
Requires-Dist: mypy>=1.0; extra == "dev"
Requires-Dist: pip-audit>=2.6.0; extra == "dev"
Requires-Dist: safety>=2.3.0; extra == "dev"
Requires-Dist: types-PyYAML; extra == "dev"
Requires-Dist: types-requests; extra == "dev"
Requires-Dist: types-psutil; extra == "dev"
Requires-Dist: types-cachetools; extra == "dev"
Requires-Dist: types-setuptools; extra == "dev"
Requires-Dist: types-aiofiles; extra == "dev"
Requires-Dist: scipy-stubs; extra == "dev"
Requires-Dist: click; extra == "dev"
Requires-Dist: semantic-version; extra == "dev"
Requires-Dist: packaging; extra == "dev"
Provides-Extra: test
Requires-Dist: pytest>=7.0; extra == "test"
Requires-Dist: pytest-asyncio>=0.21.0; extra == "test"
Requires-Dist: pytest-benchmark>=4.0.0; extra == "test"
Requires-Dist: pytest-timeout>=2.1.0; extra == "test"
Requires-Dist: pytest-cov>=4.0.0; extra == "test"
Requires-Dist: coverage[toml]>=7.0; extra == "test"
Requires-Dist: memory-profiler>=0.60.0; extra == "test"
Requires-Dist: psutil>=5.9.0; extra == "test"
Provides-Extra: performance
Requires-Dist: memory-profiler>=0.60.0; extra == "performance"
Requires-Dist: psutil>=5.9.0; extra == "performance"
Requires-Dist: pympler>=1.0.0; extra == "performance"
Requires-Dist: pytest-memprof>=0.2.0; extra == "performance"
Provides-Extra: visualization
Requires-Dist: matplotlib>=3.5.0; extra == "visualization"
Provides-Extra: full
Requires-Dist: fastapi>=0.100.0; extra == "full"
Requires-Dist: uvicorn>=0.23.0; extra == "full"
Requires-Dist: faiss-cpu>=1.7.0; extra == "full"
Requires-Dist: annoy>=1.17.0; extra == "full"
Requires-Dist: matplotlib>=3.5.0; extra == "full"
Provides-Extra: security-constraints
Requires-Dist: PyPDF2!=1.28.6; extra == "security-constraints"
Requires-Dist: langchain-community>=0.2.5; extra == "security-constraints"
Requires-Dist: flask>=3.1.0; extra == "security-constraints"
Requires-Dist: sqlitedict!=2.1.0; extra == "security-constraints"
Requires-Dist: requests>=2.32.0; extra == "security-constraints"
Requires-Dist: jinja2>=3.1.4; extra == "security-constraints"
Requires-Dist: urllib3>=2.0.0; extra == "security-constraints"
Requires-Dist: cryptography>=43.0.0; extra == "security-constraints"
Requires-Dist: pillow>=10.4.0; extra == "security-constraints"
Requires-Dist: lxml>=5.0.0; extra == "security-constraints"
Requires-Dist: setuptools>=70.0.0; extra == "security-constraints"
Requires-Dist: certifi>=2024.8.30; extra == "security-constraints"
Requires-Dist: transformers>=4.53.2; extra == "security-constraints"
Dynamic: license-file
